setup.py
iTesting/__init__.py
iTesting/main.py
iTesting.egg-info/PKG-INFO
iTesting.egg-info/SOURCES.txt
iTesting.egg-info/dependency_links.txt
iTesting.egg-info/entry_points.txt
iTesting.egg-info/not-zip-safe
iTesting.egg-info/requires.txt
iTesting.egg-info/top_level.txt
iTesting/test_data/__init__.py
iTesting/tests/__init__.py
iTesting/tests/test_iTesting.py