Metadata-Version: 1.0
Name: iTesting
Version: 0.5
Summary: This is a demo framework
Home-page: https://www.helloqa.com
Author: kevin.cai
Author-email: testertalk@outlook.com
License: MIT
Platform: UNKNOWN
